AUTHORS.rst
CONTRIBUTING.rst
HISTORY.rst
LICENSE
MANIFEST.in
README.rst
setup.cfg
setup.py
docs/Makefile
docs/authors.rst
docs/conf.py
docs/contributing.rst
docs/history.rst
docs/index.rst
docs/installation.rst
docs/make.bat
docs/readme.rst
docs/usage.rst
docs/_build/html/_static/file.png
docs/_build/html/_static/minus.png
docs/_build/html/_static/plus.png
specclassify/__init__.py
specclassify/_baseclasses.py
specclassify/classify.py
specclassify/misc.py
specclassify/similarity_measures.py
specclassify/version.py
specclassify.egg-info/PKG-INFO
specclassify.egg-info/SOURCES.txt
specclassify.egg-info/dependency_links.txt
specclassify.egg-info/not-zip-safe
specclassify.egg-info/requires.txt
specclassify.egg-info/top_level.txt
specclassify/classifiers/__init__.py
specclassify/classifiers/euclidian.py
specclassify/classifiers/hybrid.py
specclassify/classifiers/random_forest.py
specclassify/classifiers/sam.py
specclassify/classifiers/sid.py