Metadata-Version: 1.1
Name: specclassify
Version: 0.2.2
Summary: A Python package for multi- or hyperspectral image classification.
Home-page: https://gitext.gfz-potsdam.de/geomultisens/specclassify
Author: Daniel Scheffler
Author-email: daniel.scheffler@gfz-potsdam.de
License: GNU General Public License v3
Keywords: specclassify,remote sensing,multispectral,hyperspectral,image classification
Platform: UNKNOWN
Classifier: Development Status :: 2 - Pre-Alpha
Classifier: Intended Audience :: Developers
Classifier: License :: OSI Approved :: GNU General Public License v3 (GPLv3)
Classifier: Natural Language :: English
Classifier: Programming Language :: Python :: 2
Classifier: Programming Language :: Python :: 2.7
Classifier: Programming Language :: Python :: 3
Classifier: Programming Language :: Python :: 3.4
Classifier: Programming Language :: Python :: 3.5
Classifier: Programming Language :: Python :: 3.6
Classifier: Programming Language :: Python :: 3.7
Classifier: Programming Language :: Python :: 3.8
